{
  "url": "https://mp.weixin.qq.com/s?__biz=MzYzOTU1NTUzNw%3D%3D&mid=2247484348&idx=1&sn=a0b843a296f24d44d5f955d936aa1a07",
  "article_id": "A059",
  "title": "“高质量发展”~",
  "published_at": "2024-01-22",
  "published_at_for_filename": "2024-01-22-2106",
  "account_name": "天玑",
  "clean_text": "“高质量发展”~\n\n“高质量发展”~\n\n原创\n天玑\n天玑\n金渐成\n\n2024年1月22日 21:06\n\n在小说阅读器读本章\n\n去阅读\n\n在小说阅读器中沉浸阅读\n\n大A今天击穿2760点，超5000只个股绿增长；日经225指数收盘涨1.62%，再创34年来新高。\n\n如果以韩国济州岛为分界线，这股市具有强烈的“东升西落”特征；有人说，这是“环中牛市经济区”，我义愤填膺地反驳他“台湾也是咱们的一部分”，台湾股市没熊......\n\n投资三大错觉：楼市到底了、A股到底了、港股到底了。\n\n腾讯今天跌到262，我盯着好几天，一直没有出仓，等300附近再出一部分，现在成本70多；美团今天也跌到65，美团我之前观察过一阵子，后来放弃了，担心又来\n个“高质量发展\n的指导”。\n\n现在看到“高质量发展”这几个字，我会有点发麻，这几年在这几个字上亏掉的钱也有一套大平层了。无论它怎么变更用语和语境，我都能认得，就算变成一头猪，我也能在猪圈里一眼认出它，“RNM，还钱！”\n\n“高质量发展”的前提，是让大家兜里有钱，有钱会消费，消费上去了，企业自然也会做产业升级。而不是兜里光光，只剩嘴上喊口号，那就是形式主义。\n\n幼儿园时，从领导来园检查的那个下午开始，我这一生与形式主义结下不解之缘，所以我一直都很讨厌形式主义，这也是我不爱开会、不爱年会、不爱上台发言的原因之一。\n\n... ...\n\n傍晚在公司泡茶，和一90后伙伴聊起婚姻这个话题。\n\n说到过年回家被催婚这个话题，她问我怎么看到婚姻，是不是一定要结婚？\n\n我问她要听真话，还是安慰话？真话是：\n底层的婚姻，为了生存相互抱团，是必需品，一定要有；中层的婚姻为了发展，1+1＞2，可有可无；上层的婚姻，为了利益，资源整合，是奢侈品，可以没有\n。\n\n很现实的社会规则是，对于女孩子来说，男性的“硬通货”是经济条件好；对于男性来说，女孩子的“硬通货”是年轻。这么说虽然有点赤裸裸，但多经历些，自然就明白。如果你有不同意见，那就以你的为准。\n\n认识的一位女孩，过去有点“捞女”的特征，现在依旧沉迷于路径依赖，然而大环境不好，有钱男人的钱也没那么好捞了；我曾劝过她转型，不要钱，要资源，能把资源转化成经济效益，是自己能力强，而且会有源源不断的钱。\n目前来看，\n她似乎没听进去。\n\n现在不比以前了，以前还能有“嫁入豪门”的说法，现在？洗洗睡吧。现在有钱男人，一个个都精明着呢。\n想嫁给有钱人，\n也要看看\n自身的情况，美貌是一种资源，但并不稀缺。\n\n当然，要不要结婚，\n主要看自身的条件、结果、选择和取舍\n。\n\n这位90后的女孩说，据她所知，离婚后带娃的女性，特别是美国女性，一样也不愁找对象。好家伙，这个就问到熟悉的领域了。\n\n美国的男人喜欢离异带娃的女性，实际上是因为随着孩子判给女方，房子车子这些，通常会给到女方，同时男的要定时向女方支付孩子的抚养费，直到孩子成年或女方再婚。\n\n这样一来，带娃女方离异后再谈的男人，可以永远不结婚只谈恋爱，不用养她和她的孩子，一家人一起吃她前夫就行了。\n\n这也是为什么美国女人被求婚时常常泪流满面，因为这潜台词是：我要把房子、车子、票子给你了...\n\n当然，如果前夫撑不住，开始破罐子破摔，拒绝再打工赚钱，做个流浪汉，那么这一家“吃绝户”的好日子自然会立刻到头。这也是为啥美国特别有才华的流浪汉超多的原因之一。\n\n至于“要不要生孩子”这个问题，反而应该谨慎。\n\n寄希望于他\n会充实你无趣的下半生，\n维系你脆弱的婚姻，\n为你的晚年生活提供保障。\n他幼年时，有的人只是给\n娃\n提供了一口饱饭，照样\n在他\n成年之后藉“养育之恩”向他\n索取，以那点零星的情感为缚，在身体上和精神上缚\n他\n一生，这种我做不来。\n\n除了爱，任何有所企图的生养都是不道德的，\n既然擅自把他带到这个复杂的世界上来，对他好是天经地义，不要动不动就打骂\n，他是人，\n不是\n工具\n。\n\n预览时标签不可点\n\n关闭\n\n更多\n\n名称已清空\n\n微信扫一扫赞赏作者\n\n喜欢作者\n其它金额\n\n赞赏后展示我的头像\n\n作品\n\n暂无作品\n\n喜欢作者\n\n其它金额\n\n¥\n\n最低赞赏 ¥0\n\n确定\n\n返回\n\n其它金额\n\n更多\n\n赞赏金额\n\n¥\n\n最低赞赏 ¥0\n\n1\n\n2\n\n3\n\n4\n\n5\n\n6\n\n7\n\n8\n\n9\n\n0\n\n.\n\n历史文章 · 目录\n\n#历史文章\n\n上一篇\n紧急撤离~\n下一篇\n“祖传秘诀”\n\n作者提示: 素材来源官方媒体/网络新闻\n\n关闭\n\n更多\n\n搜索「」网络结果\n\n关闭\n\n调整当前正文文字大小\n\n更多\n\n100%\n\n​\n\n留言\n\n暂无留言\n\n1条留言\n\n已无更多数据\n\n发消息\n\n写留言:\n\n微信扫一扫\n\n关注该公众号\n\n继续滑动看下一个\n\n轻触阅读原文\n\n金渐成\n\n向上滑动看下一个\n\n当前内容可能存在未经审核的第三方商业营销信息，请确认是否继续访问。\n\n继续访问\n取消\n\n微信公众平台广告规范指引\n\n知道了\n\n微信扫一扫\n\n使用小程序\n\n取消\n允许\n\n取消\n允许\n\n取消\n允许\n\n×\n分析\n\n微信扫一扫可打开此内容，\n\n使用完整服务\n\n金渐成\n\n已关注\n\n赞\n\n分享\n\n推荐\n\n写留言\n\n：\n，\n，\n，\n，\n，\n，\n，\n，\n，\n，\n，\n，\n。\n视频\n小程序\n赞\n，轻点两下取消赞\n在看\n，轻点两下取消在看\n分享\n留言\n收藏\n听过\n\n可在「公众号 > 右上角\n> 划线」找到划线过的内容\n\n我知道了\n\n,\n\n,\n\n选择留言身份\n\n留言\n\n暂无留言\n\n1条留言\n\n已无更多数据\n\n发消息\n\n写留言:\n\n关闭\n\n更多\n\n关闭\n\n历史文章\n\n详情\n\n更多\n\n正在加载\n\n关闭\n\n确认提交投诉\n\n你可以补充投诉原因（选填）\n\n确定",
  "mentioned_assets": [
    "RNM"
  ],
  "core_thesis": "",
  "buy_or_accumulate_conditions": [],
  "hold_conditions": [],
  "reduce_or_exit_conditions": [],
  "risk_notes": [],
  "source_evidence": []
}
